odoo8_addon_account_analytic_project-8.0.1.0.0.99.dev21-py2.7-nspkg.pth
odoo8_addon_account_analytic_project-8.0.1.0.0.99.dev21.dist-info/METADATA
odoo8_addon_account_analytic_project-8.0.1.0.0.99.dev21.dist-info/RECORD
odoo8_addon_account_analytic_project-8.0.1.0.0.99.dev21.dist-info/WHEEL
odoo8_addon_account_analytic_project-8.0.1.0.0.99.dev21.dist-info/namespace_packages.txt
odoo8_addon_account_analytic_project-8.0.1.0.0.99.dev21.dist-info/top_level.txt
odoo_addons/account_analytic_project/README.rst
odoo_addons/account_analytic_project/__init__.py
odoo_addons/account_analytic_project/__openerp__.py
odoo_addons/account_analytic_project/i18n/account_analytic_project.pot
odoo_addons/account_analytic_project/i18n/ca.po
odoo_addons/account_analytic_project/i18n/de.po
odoo_addons/account_analytic_project/i18n/el_GR.po
odoo_addons/account_analytic_project/i18n/es.po
odoo_addons/account_analytic_project/i18n/es_MX.po
odoo_addons/account_analytic_project/i18n/fi.po
odoo_addons/account_analytic_project/i18n/fr.po
odoo_addons/account_analytic_project/i18n/hr.po
odoo_addons/account_analytic_project/i18n/nl.po
odoo_addons/account_analytic_project/i18n/pt.po
odoo_addons/account_analytic_project/i18n/pt_BR.po
odoo_addons/account_analytic_project/i18n/pt_PT.po
odoo_addons/account_analytic_project/i18n/sk_SK.po
odoo_addons/account_analytic_project/i18n/sl.po
odoo_addons/account_analytic_project/i18n/zh_CN.po
odoo_addons/account_analytic_project/model/__init__.py
odoo_addons/account_analytic_project/model/account_analytic_account.py
odoo_addons/account_analytic_project/static/description/icon.png
odoo_addons/account_analytic_project/tests/__init__.py
odoo_addons/account_analytic_project/tests/test_account_analytic_project.py
odoo_addons/account_analytic_project/view/account_analytic_account.xml
